dpypi/__init__.py
dpypi/connections/__init__.py
dpypi/connections/connection.py
dpypi/connections/github_connection.py
dpypi/connections/local_connection.py
dpypi/serve.py
dpypi/web_utils.py
dpypi/wheel.py
dynamic_pypi-0.6.5.1.dist-info/LICENSE.md
dynamic_pypi-0.6.5.1.dist-info/METADATA
dynamic_pypi-0.6.5.1.dist-info/WHEEL
dynamic_pypi-0.6.5.1.dist-info/entry_points.txt
dynamic_pypi-0.6.5.1.dist-info/RECORD
