Metadata-Version: 2.1
Name: dynamic-pypi
Version: 0.6.5.1
Summary: 
Author: parnell
Author-email: 3028114+parnell@users.noreply.github.com
Requires-Python: >=3.10,<4.0
Classifier: Programming Language :: Python :: 3
Classifier: Programming Language :: Python :: 3.10
Classifier: Programming Language :: Python :: 3.11
Classifier: Programming Language :: Python :: 3.12
Requires-Dist: pi-conf (>=0.7.7.5,<0.8.0.0)
Requires-Dist: pygithub (>=2.2.0,<3.0.0)
